Yaml8/Yaml.py
Yaml8/__init__.py
Yaml8-0.1.2.dist-info/LICENSE
Yaml8-0.1.2.dist-info/METADATA
Yaml8-0.1.2.dist-info/WHEEL
Yaml8-0.1.2.dist-info/top_level.txt
Yaml8-0.1.2.dist-info/RECORD
