Metadata-Version: 2.1
Name: Yaml8
Version: 0.1.2
Summary: Python package to make getting yaml easier and cleaner
Home-page: https://github.com/AppDevIn/Yaml-Python
Author: AppDevIn Sliver
Author-email:  teamprojectlive@example.com
License: UNKNOWN
Project-URL: Bug Tracker, https://github.com/AppDevIn/Yaml-Python/issues
Platform: UNKNOWN
Classifier: Programming Language :: Python :: 3
Classifier: License :: OSI Approved :: MIT License
Classifier: Operating System :: OS Independent
Requires-Python: >=3.6
License-File: LICENSE
